structhub/__init__.py
structhub/client.py
structhub-0.0.4.dist-info/LICENSE
structhub-0.0.4.dist-info/METADATA
structhub-0.0.4.dist-info/WHEEL
structhub-0.0.4.dist-info/top_level.txt
structhub-0.0.4.dist-info/RECORD
