Metadata-Version: 2.1
Name: structhub
Version: 0.0.4
License-File: LICENSE
Requires-Dist: requests >=2.0.0
